impact_stack/auth_wsgi_middleware/__init__.py
impact_stack_auth_wsgi_middleware-0.7.0.dist-info/licenses/LICENSE
impact_stack_auth_wsgi_middleware-0.7.0.dist-info/METADATA
impact_stack_auth_wsgi_middleware-0.7.0.dist-info/WHEEL
impact_stack_auth_wsgi_middleware-0.7.0.dist-info/top_level.txt
impact_stack_auth_wsgi_middleware-0.7.0.dist-info/RECORD
