Metadata-Version: 2.4
Name: impact-stack-auth-wsgi-middleware
Version: 0.7.0
Author-email: Roman Zimmermann <roman@more-onion.com>
License-File: LICENSE
Requires-Dist: impact-stack-rest>=0.3.0
Requires-Dist: itsdangerous
Requires-Dist: redis
Requires-Dist: werkzeug>=2.3
Provides-Extra: dev
Requires-Dist: black; extra == "dev"
Requires-Dist: fakeredis; extra == "dev"
Requires-Dist: flask; extra == "dev"
Requires-Dist: flask-jwt-extended; extra == "dev"
Requires-Dist: isort; extra == "dev"
Requires-Dist: pre-commit; extra == "dev"
Requires-Dist: pylint; extra == "dev"
Requires-Dist: pytest; extra == "dev"
Requires-Dist: pytest-cov; extra == "dev"
Requires-Dist: requests-mock; extra == "dev"
Requires-Dist: twine; extra == "dev"
Dynamic: license-file
